zwog/__init__.py
zwog/constants.py
zwog/utils.py
zwog-1.1.0.dist-info/LICENSE
zwog-1.1.0.dist-info/METADATA
zwog-1.1.0.dist-info/WHEEL
zwog-1.1.0.dist-info/entry_points.txt
zwog-1.1.0.dist-info/RECORD
