Metadata-Version: 2.1
Name: zwog
Version: 1.1.0
Summary: Zwift workout generator
Home-page: https://github.com/tare/zwog
License: BSD-3-Clause
Keywords: zwift,cycling,workout
Author: Tarmo Äijö
Author-email: tarmo.aijo@gmail.com
Requires-Python: >=3.10,<4.0
Classifier: Development Status :: 5 - Production/Stable
Classifier: Intended Audience :: Other Audience
Classifier: License :: OSI Approved :: BSD License
Classifier: Programming Language :: Python :: 3
Classifier: Programming Language :: Python :: 3.10
Classifier: Programming Language :: Python :: 3.11
Classifier: Programming Language :: Python :: 3.12
Classifier: Programming Language :: Python :: 3.13
Classifier: Topic :: Games/Entertainment
Requires-Dist: lark (>=1.1.2)
Project-URL: Bug Tracker, https://github.com/tare/zwog/issues
Project-URL: Repository, https://github.com/tare/zwog
